{"name":"sequence","_rev":7,"original_tree":["define",{"name":"simple"},[["define",{"ping":null},[["amqp",{"command":"/ping/ping","reply_anyway":true,"queue":"ping","reply_queue":"ping"},[]]]],["define",{"pong":null},[["amqp",{"command":"/pong/pong","queue":"pong"},[]]]],["define",{"shout":null},[["echo",{"Error occured... ${f.state}":null},[]]]],["sequence",{"on_error":"shout"},[["participant",{"alpha":null},[]],["participant",{"logger":null},[]],["ping",{},[]],["participant",{"logger":null},[]],["pong",{},[]],["paritcipant",{"logger":null},[]]]]]],"variables":{"simple":["0",["define",{"name":"simple"},[["define",{"ping":null},[["amqp",{"command":"/ping/ping","reply_anyway":true,"queue":"ping","reply_queue":"ping"},[]]]],["define",{"pong":null},[["amqp",{"command":"/pong/pong","queue":"pong"},[]]]],["define",{"shout":null},[["echo",{"Error occured... ${f.state}":null},[]]]],["sequence",{"on_error":"shout"},[["participant",{"alpha":null},[]],["participant",{"logger":null},[]],["ping",{},[]],["participant",{"logger":null},[]],["pong",{},[]],["paritcipant",{"logger":null},[]]]]]]],"pong":["0_1",["define",{"pong":null},[["amqp",{"command":"/pong/pong","queue":"pong"},[]]]]],"shout":["0_2",["define",{"shout":null},[["echo",{"Error occured... ${f.state}":null},[]]]]],"ping":["0_0",["define",{"ping":null},[["amqp",{"command":"/ping/ping","reply_anyway":true,"queue":"ping","reply_queue":"ping"},[]]]]]},"on_timeout":null,"put_at":"2010-09-25 07:59:09.309688 UTC","_id":"0!!20100925-norozeke","applied_workitem":{"fields":{},"fei":{"sub_wfid":null,"wfid":"20100925-norozeke","engine_id":"engine","expid":"0"}},"type":"expressions","created_time":"2010-09-25 07:59:09.280719 UTC","on_cancel":null,"parent_id":null,"forgotten":null,"children":[{"sub_wfid":null,"wfid":"20100925-norozeke","engine_id":"engine","expid":"0_3"}],"tagname":null,"fei":{"sub_wfid":null,"wfid":"20100925-norozeke","engine_id":"engine","expid":"0"},"on_error":null}