{"name":"sequence","_rev":1,"original_tree":["define",{},[["sequence",{},[["repeat",{},[["ping",{},[]],["log",{},[]],["pong",{},[]],["log",{},[]],["break",{"if":"${f.count} >= 6"},[]]]]]]]],"variables":{},"on_timeout":null,"put_at":"2010-09-19 18:32:17.189695 UTC","_id":"0!!20100919-bebidujapi","applied_workitem":{"fields":{},"fei":{"sub_wfid":null,"wfid":"20100919-bebidujapi","engine_id":"engine","expid":"0"}},"type":"expressions","created_time":"2010-09-19 18:32:17.188188 UTC","on_cancel":null,"parent_id":null,"forgotten":null,"children":[{"sub_wfid":null,"wfid":"20100919-bebidujapi","engine_id":"engine","expid":"0_0"}],"tagname":null,"fei":{"sub_wfid":null,"wfid":"20100919-bebidujapi","engine_id":"engine","expid":"0"},"on_error":null}